pytest_markers_presence.py
pytest_markers_presence-0.13.1.dist-info/AUTHORS.rst
pytest_markers_presence-0.13.1.dist-info/LICENSE
pytest_markers_presence-0.13.1.dist-info/METADATA
pytest_markers_presence-0.13.1.dist-info/WHEEL
pytest_markers_presence-0.13.1.dist-info/entry_points.txt
pytest_markers_presence-0.13.1.dist-info/top_level.txt
pytest_markers_presence-0.13.1.dist-info/RECORD
