Metadata-Version: 2.1
Name: pytest-markers-presence
Version: 0.13.1
Summary: A simple plugin to detect missed pytest tags and markers"
Home-page: https://github.com/livestreamx/pytest-markers-presence
Author: Vladislav Mukhamatnurov
Author-email: livestreamepidemz@yandex.ru
Maintainer: Vladislav Mukhamatnurov
Maintainer-email: livestreamepidemz@yandex.ru
License: MIT
Classifier: Development Status :: 4 - Beta
Classifier: Framework :: Pytest
Classifier: Intended Audience :: Developers
Classifier: Topic :: Software Development :: Testing
Classifier: Programming Language :: Python :: 3.7
Classifier: Programming Language :: Python :: 3.8
Classifier: Programming Language :: Python :: 3.9
Classifier: Programming Language :: Python :: Implementation :: CPython
Classifier: Programming Language :: Python :: Implementation :: PyPy
Classifier: Operating System :: OS Independent
Classifier: License :: OSI Approved :: MIT License
Requires-Python: >=3.7
License-File: LICENSE
License-File: AUTHORS.rst
Requires-Dist: pytest>=6.0
Requires-Dist: allure-pytest>=2.8.19
Requires-Dist: pydantic>=2.0
